Metadata-Version: 2.1
Name: convert-api-Tigromag
Version: 1.0.0
Summary: Python module for convert numbers(in various number systems)
Home-page: https://github.com/Tigromag/convert_api
Author: Tigromag
Author-email: tigromag010@gmail.com
License: Apache license, Version 2.0, see LICENSE file
Download-URL: https://github.com/Tigromag/convert_api/archive/refs/heads/main.zip
Platform: UNKNOWN
Classifier: License :: OSI Approved :: Apache Software License
Classifier: Operating System :: OS Independent
Classifier: Intended Audience :: End Users/Desktop
Classifier: Intended Audience :: Developers
Classifier: Programming Language :: Python
Classifier: Programming Language :: Python :: 3
Classifier: Programming Language :: Python :: 3.6
Classifier: Programming Language :: Python :: 3.7
Classifier: Programming Language :: Python :: 3.8
Classifier: Programming Language :: Python :: Implementation :: PyPy
Classifier: Programming Language :: Python :: Implementation :: CPython
